oasm/__init__.py
oasm-0.1.5.dist-info/METADATA
oasm-0.1.5.dist-info/WHEEL
oasm-0.1.5.dist-info/top_level.txt
oasm-0.1.5.dist-info/RECORD
